{
  "id": "20260716-github-1cd4e4f553",
  "title": "livekit/livekit",
  "source": "github_trending",
  "source_url": "https://github.com/livekit/livekit",
  "summary": "livekit/livekit 是一个端到端的实时通信栈，用于连接人类与AI，基于Go语言开发，在GitHub上获得近2万星标。",
  "content": "livekit/livekit 是一个开源的实时通信平台，专注于构建端到端的实时音视频和数据通道，以连接人类与AI系统。该项目使用Go语言编写，在GitHub上拥有19782颗星标和2156个分支，近期每日新增星标约22个。它被归类为GitHub热点项目中的Go语言类别，适用于需要低延迟、高可靠性的实时交互场景，如AI助手、远程协作和直播等。",
  "tags": [
    "实时通信",
    "AI",
    "Go",
    "音视频",
    "开源"
  ],
  "status": "draft",
  "published_at": null,
  "collected_at": "2026-07-16T19:28:34+08:00",
  "language": "Go",
  "score": 8.5,
  "metadata": {
    "author": "livekit",
    "stars": 19782,
    "forks": 2156,
    "daily_stars": 22,
    "weekly_stars": null,
    "monthly_stars": null,
    "stars_baseline_date": null,
    "feed_name": null,
    "category": "GitHub 热点 · Go"
  }
}
