{
  "id": "20260716-github-cd661dd6c1",
  "title": "larksuite/cli",
  "source": "github_trending",
  "source_url": "https://github.com/larksuite/cli",
  "summary": "飞书官方 CLI 工具，专为人类和 AI 代理设计，覆盖 Messenger、Docs、Base、Sheets、Calendar、Mail、Tasks、Meetings 等核心业务域，提供 200+ 命令和 20+ AI 代理技能。",
  "content": "larksuite/cli 是飞书（Lark/Feishu）官方维护的命令行工具，旨在为开发者和 AI 代理提供高效、统一的接口来管理飞书生态中的各项服务。该工具涵盖了即时通讯、文档、多维表格、电子表格、日历、邮件、任务、会议等核心业务域，支持超过 200 条命令和 20 多种 AI 代理技能，能够显著提升自动化工作流和智能交互的效率。项目采用 Go 语言开发，在 GitHub 上获得了 15669 颗星和 1239 个 fork，周增长 363 星，属于 GitHub 热点 Go 项目。",
  "tags": [
    "飞书",
    "CLI",
    "AI代理",
    "Go",
    "自动化",
    "办公效率"
  ],
  "status": "draft",
  "published_at": null,
  "collected_at": "2026-07-16T19:28:43+08:00",
  "language": "Go",
  "score": 8.5,
  "metadata": {
    "author": "larksuite",
    "stars": 15669,
    "forks": 1239,
    "daily_stars": null,
    "weekly_stars": 363,
    "monthly_stars": null,
    "stars_baseline_date": null,
    "feed_name": null,
    "category": "GitHub 热点 · Go"
  }
}
