{
  "id": "20260624-github-894460bdca",
  "title": "Adam-CAD/CADAM",
  "source": "github_trending",
  "source_url": "https://github.com/Adam-CAD/CADAM",
  "summary": "CADAM 是一个开源的文本转 CAD 网页应用，允许用户通过自然语言描述生成 CAD 模型。",
  "content": "CADAM 是一个基于 TypeScript 开发的开源项目，旨在通过自然语言输入直接生成 CAD 模型。用户只需描述设计需求，应用即可自动创建对应的 CAD 文件。该项目在 GitHub 上获得了 4618 颗星和 574 个 fork，周增长 574 颗星，属于 GitHub 热点项目。其核心功能是降低 CAD 建模门槛，使非专业用户也能快速生成设计。",
  "tags": [
    "CAD",
    "文本转CAD",
    "开源",
    "TypeScript",
    "自然语言处理",
    "3D建模",
    "GitHub热点"
  ],
  "status": "draft",
  "published_at": null,
  "collected_at": "2026-06-24T19:01:49+08:00",
  "language": "TypeScript",
  "score": 8.5,
  "metadata": {
    "author": "Adam-CAD",
    "stars": 4618,
    "forks": 574,
    "daily_stars": null,
    "weekly_stars": 574,
    "monthly_stars": null,
    "stars_baseline_date": null,
    "feed_name": null,
    "category": "GitHub 热点 · TypeScript"
  }
}
