{
  "id": "20260610-github-b1db5a1ca6",
  "title": "paritytech/polkadot-sdk",
  "source": "github_trending",
  "source_url": "https://github.com/paritytech/polkadot-sdk",
  "summary": "Parity Polkadot 区块链 SDK",
  "content": "Parity Polkadot 区块链 SDK 是一个用于构建和部署 Polkadot 区块链生态系统的软件开发工具包。它提供了核心组件和库，支持开发者创建平行链、智能合约以及与 Polkadot 网络交互。该 SDK 由 Parity Technologies 维护，基于 Rust 语言开发，具有高性能和安全性。",
  "tags": [
    "Polkadot",
    "区块链",
    "SDK",
    "Rust",
    "Parity",
    "平行链"
  ],
  "status": "draft",
  "published_at": null,
  "collected_at": "2026-06-10T19:15:26+08:00",
  "language": "Rust",
  "score": 8.5,
  "metadata": {
    "author": "paritytech",
    "stars": 2773,
    "forks": 1206,
    "daily_stars": 0,
    "weekly_stars": null,
    "monthly_stars": null,
    "stars_baseline_date": null,
    "feed_name": null,
    "category": "GitHub 热点 · Rust"
  }
}
