{
  "id": "20260724-github-56498c5feb",
  "title": "dottxt-ai/outlines",
  "source": "github_trending",
  "source_url": "https://github.com/dottxt-ai/outlines",
  "summary": "dottxt-ai/outlines 是一个专注于生成结构化输出的 Python 库，在 GitHub 上获得广泛关注，拥有超过 15,000 颗星。",
  "content": "该项目旨在为 AI 模型提供结构化输出生成能力，可能涉及约束解码、格式控制等技术，以提升生成结果的可控性和准确性。其高星数和活跃的社区贡献表明其在 AI 技术领域具有重要价值。",
  "tags": [
    "结构化输出",
    "AI 生成",
    "Python 库",
    "约束解码",
    "GitHub 热点"
  ],
  "status": "draft",
  "published_at": null,
  "collected_at": "2026-07-24T19:37:39+08:00",
  "language": "Python",
  "score": 8.5,
  "metadata": {
    "author": "dottxt-ai",
    "stars": 15303,
    "forks": 812,
    "daily_stars": 56,
    "weekly_stars": 783,
    "monthly_stars": null,
    "stars_baseline_date": null,
    "feed_name": null,
    "category": "GitHub 热点 · Python"
  }
}
