{
  "id": "20260522-github-3b42e75165",
  "title": "derailed/k9s",
  "source": "github_trending",
  "source_url": "https://github.com/derailed/k9s",
  "summary": "K9s 是一个基于 Go 语言开发的 Kubernetes CLI 工具，旨在通过终端界面优雅地管理和监控 Kubernetes 集群。",
  "content": "K9s 是一个流行的开源 Kubernetes 集群管理工具，它提供了一个基于终端的用户界面，允许用户通过键盘快捷键和命令来浏览、监控和管理 Kubernetes 资源。该工具支持实时查看 Pod 日志、执行命令、编辑资源、查看集群状态等功能，极大地简化了 Kubernetes 的日常运维工作。项目由 derailed 开发，在 GitHub 上拥有超过 33,000 颗星，社区活跃，持续更新。",
  "tags": [
    "Kubernetes",
    "CLI",
    "Go",
    "集群管理",
    "DevOps",
    "终端工具"
  ],
  "status": "draft",
  "published_at": null,
  "collected_at": "2026-05-22T19:01:49+08:00",
  "language": "Go",
  "score": 9.0,
  "metadata": {
    "author": "derailed",
    "stars": 33709,
    "forks": 2166,
    "daily_stars": 14,
    "weekly_stars": null,
    "monthly_stars": null,
    "stars_baseline_date": null,
    "feed_name": null,
    "category": "GitHub 热点 · Go"
  }
}
