{
  "id": "20260516-github-3b6ae67581",
  "title": "rustdesk/rustdesk",
  "source": "github_trending",
  "source_url": "https://github.com/rustdesk/rustdesk",
  "summary": "RustDesk 是一款开源的远程桌面应用，支持自托管，可作为 TeamViewer 的替代方案。",
  "content": "RustDesk 是一个用 Rust 语言开发的开源远程桌面软件，旨在提供自托管解决方案，作为 TeamViewer 的替代品。该项目在 GitHub 上拥有超过 11.4 万星标和 1.7 万分支，每日新增约 100 星标，显示出极高的社区关注度和活跃度。其核心优势在于开源、安全、可自建服务器，适合需要隐私保护和定制化的用户。",
  "tags": [
    "远程桌面",
    "开源",
    "自托管",
    "Rust",
    "TeamViewer替代"
  ],
  "status": "draft",
  "published_at": null,
  "collected_at": "2026-05-16T18:28:03+08:00",
  "language": "Rust",
  "score": 9.5,
  "metadata": {
    "author": "rustdesk",
    "stars": 114318,
    "forks": 17179,
    "daily_stars": 100,
    "weekly_stars": null,
    "monthly_stars": null,
    "stars_baseline_date": null,
    "feed_name": null,
    "category": "GitHub 热点 · Rust"
  }
}
