{
  "id": "20260710-github-cb0230bf14",
  "title": "jesseduffield/lazydocker",
  "source": "github_trending",
  "source_url": "https://github.com/jesseduffield/lazydocker",
  "summary": "Lazydocker 是一个基于 Go 语言开发的 Docker 管理终端工具，旨在通过更懒的方式简化 Docker 容器的日常操作。它提供了直观的 TUI 界面，让用户无需记忆复杂命令即可轻松管理容器、镜像、卷和网络等资源。",
  "content": "Lazydocker 由知名开发者 jesseduffield 创建，其核心理念是“以更懒的方式管理一切 Docker”。该项目在 GitHub 上拥有超过 5.1 万星标，社区活跃度高。它通过终端用户界面（TUI）提供实时监控、一键操作和日志查看等功能，显著降低了 Docker 管理的学习曲线和操作复杂度。支持多容器、多服务场景下的快速导航与问题排查，适合开发者和运维人员日常使用。",
  "tags": [
    "Docker",
    "终端工具",
    "TUI",
    "容器管理",
    "Go",
    "开发者工具",
    "开源"
  ],
  "status": "draft",
  "published_at": null,
  "collected_at": "2026-07-10T20:21:43+08:00",
  "language": "Go",
  "score": 8.5,
  "metadata": {
    "author": "jesseduffield",
    "stars": 51967,
    "forks": 1648,
    "daily_stars": null,
    "weekly_stars": 406,
    "monthly_stars": null,
    "stars_baseline_date": null,
    "feed_name": null,
    "category": "GitHub 热点 · Go"
  }
}
