{
  "id": "20260719-github-58b3d2865c",
  "title": "nearai/ironclaw",
  "source": "github_trending",
  "source_url": "https://github.com/nearai/ironclaw",
  "summary": "IronClaw 是一个专注于隐私、安全和可扩展性的 Agent 操作系统。",
  "content": "IronClaw 是一个基于 Rust 开发的 Agent 操作系统，由 nearai 团队维护。该项目在 GitHub 上获得了 12524 颗星和 1475 个分支，日增星 7 颗，属于 GitHub 热点 Rust 类别。其核心设计理念是隐私、安全和可扩展性，旨在为代理（Agent）提供安全可靠的运行环境。",
  "tags": [
    "Agent OS",
    "隐私",
    "安全",
    "可扩展性",
    "Rust",
    "GitHub 热点"
  ],
  "status": "draft",
  "published_at": null,
  "collected_at": "2026-07-19T19:06:08+08:00",
  "language": "Rust",
  "score": 8.5,
  "metadata": {
    "author": "nearai",
    "stars": 12524,
    "forks": 1475,
    "daily_stars": 7,
    "weekly_stars": null,
    "monthly_stars": null,
    "stars_baseline_date": null,
    "feed_name": null,
    "category": "GitHub 热点 · Rust"
  }
}
