{
  "id": "20260705-github-9b40a0a6a0",
  "title": "Please stop the AI confidence theater",
  "source": "rss",
  "source_url": "https://www.elenaverna.com/p/please-stop-the-ai-confidence-theater",
  "summary": "文章呼吁停止AI领域的‘自信剧场’，即过度展示自信而缺乏实质验证的行为，强调需要更严谨的评估和透明度。",
  "content": "本文来自Elena Verna的博客，批评AI社区中普遍存在的‘自信剧场’现象——开发者或公司通过夸大模型能力、回避失败案例来营造虚假信心。作者主张应建立更严格的基准测试、公开失败记录，并鼓励谦逊的学术讨论，以推动AI技术的健康发展。文章在Hacker News上获得232分和257条评论，引发广泛讨论。",
  "tags": [
    "AI",
    "自信剧场",
    "透明度",
    "评估",
    "Hacker News"
  ],
  "status": "draft",
  "published_at": "2026-07-03T12:51:17+00:00",
  "collected_at": "2026-07-05T19:26:14+08:00",
  "language": "en",
  "score": 8.5,
  "metadata": {
    "feed_name": "Hacker News Best (AI related)",
    "category": "综合技术",
    "stars": null,
    "daily_stars": null,
    "weekly_stars": null,
    "monthly_stars": null,
    "stars_baseline_date": null
  }
}
