{
  "id": "20260606-github-b28cf1b789",
  "title": "temporalio/temporal",
  "source": "github_trending",
  "source_url": "https://github.com/temporalio/temporal",
  "summary": "Temporal 是一个开源的工作流引擎，用于构建可靠、可扩展的分布式应用程序，支持 Go 语言开发。",
  "content": "Temporal 是一个由 Temporal Technologies 开发的开源工作流引擎，旨在简化分布式系统中复杂工作流的构建和管理。它提供了持久性、可恢复性和可扩展性，允许开发者以代码形式定义工作流逻辑，并自动处理状态管理、重试、超时和错误处理。该项目在 GitHub 上拥有超过 2 万颗星，社区活跃，广泛应用于微服务编排、业务流程自动化等领域。",
  "tags": [
    "工作流引擎",
    "分布式系统",
    "Go",
    "微服务编排",
    "开源"
  ],
  "status": "draft",
  "published_at": null,
  "collected_at": "2026-06-06T18:39:00+08:00",
  "language": "Go",
  "score": 9.5,
  "metadata": {
    "author": "temporalio",
    "stars": 20785,
    "forks": 1634,
    "daily_stars": null,
    "weekly_stars": 183,
    "monthly_stars": null,
    "stars_baseline_date": null,
    "feed_name": null,
    "category": "GitHub 热点 · Go"
  }
}
