{
  "id": "20260515-github-fe011eb736",
  "title": "safing/portmaster",
  "source": "github_trending",
  "source_url": "https://github.com/safing/portmaster",
  "summary": "Portmaster 是一个开源的网络监控和隐私保护工具，旨在通过阻止大规模监控来维护用户自由。",
  "content": "Portmaster 由 safing 开发，是一款用 Go 语言编写的网络监控和隐私保护应用。它通过提供细粒度的网络流量控制、DNS 过滤和应用程序防火墙功能，帮助用户阻止不必要的网络连接和跟踪，从而对抗大规模监控。该项目在 GitHub 上拥有超过 1.2 万颗星，周增星数达 161，显示出社区的高度关注。其核心目标是“热爱自由，阻止大规模监控”，适用于注重隐私的用户。",
  "tags": [
    "网络监控",
    "隐私保护",
    "防火墙",
    "DNS 过滤",
    "开源",
    "Go"
  ],
  "status": "draft",
  "published_at": null,
  "collected_at": "2026-05-15T18:48:05+08:00",
  "language": "Go",
  "score": 8.5,
  "metadata": {
    "author": "safing",
    "stars": 12733,
    "forks": 496,
    "daily_stars": null,
    "weekly_stars": 161,
    "monthly_stars": null,
    "stars_baseline_date": null,
    "feed_name": null,
    "category": "GitHub 热点 · Go"
  }
}
