{
  "id": "20260609-github-55adc2b2d1",
  "title": "AlistGo/alist",
  "source": "github_trending",
  "source_url": "https://github.com/AlistGo/alist",
  "summary": "AlistGo/alist 是一个支持多存储的文件列表和 WebDAV 程序，基于 Gin 和 Solidjs 构建，在 GitHub 上获得 49629 颗星和 7951 个分支，属于 Go 语言热点项目。",
  "content": "该项目是一个功能强大的文件管理和 WebDAV 服务工具，支持多种存储后端（如本地、云存储等），使用 Go 语言开发，前端采用 Solidjs 框架。它提供统一的文件列表和访问接口，便于用户管理和分享文件。项目在 GitHub 上持续获得关注，每日新增约 13 颗星，属于 Go 语言领域的热门开源项目。",
  "tags": [
    "文件列表",
    "WebDAV",
    "多存储",
    "Go",
    "Solidjs",
    "开源",
    "GitHub 热点"
  ],
  "status": "draft",
  "published_at": null,
  "collected_at": "2026-06-09T19:03:44+08:00",
  "language": "Go",
  "score": 9.0,
  "metadata": {
    "author": "AlistGo",
    "stars": 49629,
    "forks": 7951,
    "daily_stars": 13,
    "weekly_stars": null,
    "monthly_stars": null,
    "stars_baseline_date": null,
    "feed_name": null,
    "category": "GitHub 热点 · Go"
  }
}
