{
  "id": "20260717-github-9d0975e0f3",
  "title": "dstotijn/hetty",
  "source": "github_trending",
  "source_url": "https://github.com/dstotijn/hetty",
  "summary": "Hetty 是一个用于安全研究的 HTTP 工具包，由 Go 语言开发，在 GitHub 上获得了超过 1.1 万颗星，近期日增星约 91 颗，受到安全社区关注。",
  "content": "Hetty 是一个面向安全研究人员的 HTTP 工具包，旨在简化 Web 安全测试中的 HTTP 请求与响应分析。它提供了代理、重放、日志记录等功能，帮助研究人员高效地发现和利用漏洞。该项目使用 Go 语言构建，具有跨平台、高性能的特点。当前在 GitHub 上拥有 11853 颗星和 765 个分支，日增星 91 颗，表明其活跃度和受欢迎程度较高。",
  "tags": [
    "HTTP工具包",
    "安全研究",
    "Go",
    "Web安全",
    "代理工具"
  ],
  "status": "draft",
  "published_at": null,
  "collected_at": "2026-07-17T19:18:11+08:00",
  "language": "Go",
  "score": 8.5,
  "metadata": {
    "author": "dstotijn",
    "stars": 11853,
    "forks": 765,
    "daily_stars": 91,
    "weekly_stars": null,
    "monthly_stars": null,
    "stars_baseline_date": null,
    "feed_name": null,
    "category": "GitHub 热点 · Go"
  }
}
