{
  "id": "20260717-github-3595eaeb74",
  "title": "HKUDS/nanobot",
  "source": "github_trending",
  "source_url": "https://github.com/HKUDS/nanobot",
  "summary": "HKUDS/nanobot 是一个轻量级、开源的 AI 代理，旨在集成工具、聊天和工作流，提供灵活且高效的自动化解决方案。",
  "content": "该项目由 HKUDS 团队开发，基于 Python 实现，在 GitHub 上获得了 45,796 颗星和 8,087 个分支，周增长 625 颗星，显示出较高的社区关注度。nanobot 的核心优势在于其轻量级设计，允许用户通过简单的配置将 AI 能力嵌入到各种工具和聊天系统中，并支持自定义工作流。它适合需要快速部署 AI 代理的开发者和团队，尤其适用于自动化任务和集成场景。",
  "tags": [
    "AI代理",
    "开源",
    "轻量级",
    "工作流自动化",
    "Python",
    "工具集成"
  ],
  "status": "draft",
  "published_at": null,
  "collected_at": "2026-07-17T19:18:13+08:00",
  "language": "Python",
  "score": 8.5,
  "metadata": {
    "author": "HKUDS",
    "stars": 45796,
    "forks": 8087,
    "daily_stars": null,
    "weekly_stars": 625,
    "monthly_stars": null,
    "stars_baseline_date": null,
    "feed_name": null,
    "category": "GitHub 热点 · Python"
  }
}
