{
  "id": "20260511-github-675bc1bbe6",
  "title": "hickory-dns/hickory-dns",
  "source": "github_trending",
  "source_url": "https://github.com/hickory-dns/hickory-dns",
  "summary": "基于 Rust 的 DNS 客户端、服务器和解析器",
  "content": "hickory-dns 是一个用 Rust 语言编写的 DNS 工具库，提供客户端、服务器和解析器功能。该项目在 GitHub 上获得 5220 颗星和 583 个分支，周增星 29 颗，属于 Rust 语言的热门项目。它适合需要高性能、安全 DNS 处理的场景，如网络工具开发或自定义 DNS 服务搭建。",
  "tags": [
    "DNS",
    "Rust",
    "网络工具",
    "开源"
  ],
  "status": "draft",
  "published_at": null,
  "collected_at": "2026-05-11T19:04:34+08:00",
  "language": "Rust",
  "score": 8.5,
  "metadata": {
    "author": "hickory-dns",
    "stars": 5220,
    "forks": 583,
    "daily_stars": null,
    "weekly_stars": 29,
    "monthly_stars": null,
    "stars_baseline_date": null,
    "feed_name": null,
    "category": "GitHub 热点 · Rust"
  }
}
