{
  "id": "20260511-github-5ef8a9486d",
  "title": "rust-lang/cargo",
  "source": "github_trending",
  "source_url": "https://github.com/rust-lang/cargo",
  "summary": "Rust 包管理器 — Cargo 是 Rust 编程语言的官方包管理器，负责项目的构建、依赖管理和发布。它简化了 Rust 项目的开发流程，支持自动下载依赖、编译代码、运行测试和生成文档。作为 Rust 生态系统的核心工具，Cargo 提供了强大的工作空间支持、版本控制集成和自定义构建脚本功能。",
  "content": "Cargo 是 Rust 编程语言的官方包管理器，负责项目的构建、依赖管理和发布。它简化了 Rust 项目的开发流程，支持自动下载依赖、编译代码、运行测试和生成文档。作为 Rust 生态系统的核心工具，Cargo 提供了强大的工作空间支持、版本控制集成和自定义构建脚本功能。",
  "tags": [
    "Rust",
    "包管理器",
    "构建工具",
    "依赖管理",
    "开源"
  ],
  "status": "draft",
  "published_at": null,
  "collected_at": "2026-05-11T19:04:26+08:00",
  "language": "中文",
  "score": 9.5,
  "metadata": {
    "author": "rust-lang",
    "stars": 14939,
    "forks": 2911,
    "daily_stars": 8,
    "weekly_stars": null,
    "monthly_stars": null,
    "stars_baseline_date": null,
    "feed_name": null,
    "category": "GitHub 热点 · Rust"
  }
}
