{
  "id": "20260530-github-6086f857b3",
  "title": "millionco/react-doctor",
  "source": "github_trending",
  "source_url": "https://github.com/millionco/react-doctor",
  "summary": "millionco/react-doctor 是一个 TypeScript 项目，旨在自动检测并修复 React 代码中的不良实践，充当智能代码审查助手。",
  "content": "该项目通过静态分析或运行时检查，识别 React 组件中的常见错误模式（如不必要的重新渲染、状态管理不当等），并提供自动修复建议或直接修复。它类似于一个“医生”，帮助开发者提升代码质量，尤其适合大型项目或团队协作场景。",
  "tags": [
    "React",
    "代码质量",
    "自动修复",
    "TypeScript",
    "静态分析"
  ],
  "status": "draft",
  "published_at": null,
  "collected_at": "2026-05-30T18:34:35+08:00",
  "language": "TypeScript",
  "score": 8.5,
  "metadata": {
    "author": "millionco",
    "stars": 11567,
    "forks": 376,
    "daily_stars": 148,
    "weekly_stars": null,
    "monthly_stars": null,
    "stars_baseline_date": null,
    "feed_name": null,
    "category": "GitHub 热点 · TypeScript"
  }
}
