{
  "id": "20260702-github-e5ac887c68",
  "title": "NanmiCoder/MediaCrawler",
  "source": "github_trending",
  "source_url": "https://github.com/NanmiCoder/MediaCrawler",
  "summary": "MediaCrawler 是一个多平台社交媒体数据爬虫工具，支持小红书、抖音、快手、B站、微博、百度贴吧和知乎等主流平台，可抓取帖子、视频、评论及回复等数据。",
  "content": "该项目由 NanmiCoder 开发，在 GitHub 上获得 54,986 颗星和 11,147 个 fork，周增星 2,575 颗，属于 Python 类别下的热门仓库。它提供统一的接口来爬取多个社交媒体平台的内容，包括小红书笔记和评论、抖音视频和评论、快手视频和评论、B站视频和评论、微博帖子及评论、百度贴吧帖子及评论回复、知乎问答文章及评论。适用于数据采集、舆情分析、内容研究等场景。",
  "tags": [
    "爬虫",
    "社交媒体",
    "数据采集",
    "小红书",
    "抖音",
    "快手",
    "B站",
    "微博",
    "百度贴吧",
    "知乎",
    "Python"
  ],
  "status": "draft",
  "published_at": null,
  "collected_at": "2026-07-02T18:54:31+08:00",
  "language": "Python",
  "score": 8.5,
  "metadata": {
    "author": "NanmiCoder",
    "stars": 54986,
    "forks": 11147,
    "daily_stars": null,
    "weekly_stars": 2575,
    "monthly_stars": null,
    "stars_baseline_date": null,
    "feed_name": null,
    "category": "GitHub 热点 · Python"
  }
}
