{
  "id": "20260614-github-bc4f619e9a",
  "title": "AUTOMATIC1111/stable-diffusion-webui",
  "source": "github_trending",
  "source_url": "https://github.com/AUTOMATIC1111/stable-diffusion-webui",
  "summary": "Stable Diffusion web UI 是一个基于 Gradio 库的浏览器界面，用于运行 Stable Diffusion 图像生成模型。",
  "content": "该项目由 AUTOMATIC1111 开发，是 GitHub 上最热门的 Python 项目之一，拥有 163,686 颗星和 30,368 个分支。它提供了一个直观的 Web 界面，支持文本到图像、图像到图像、图像修复、超分辨率等多种功能，并允许用户通过扩展和脚本自定义工作流。该工具极大地降低了 Stable Diffusion 的使用门槛，成为 AI 图像生成领域的重要基础设施。",
  "tags": [
    "Stable Diffusion",
    "AI 图像生成",
    "Web UI",
    "Python",
    "Gradio",
    "深度学习"
  ],
  "status": "draft",
  "published_at": null,
  "collected_at": "2026-06-14T18:58:06+08:00",
  "language": "Python",
  "score": 9.5,
  "metadata": {
    "author": "AUTOMATIC1111",
    "stars": 163686,
    "forks": 30368,
    "daily_stars": 32,
    "weekly_stars": null,
    "monthly_stars": null,
    "stars_baseline_date": null,
    "feed_name": null,
    "category": "GitHub 热点 · Python"
  }
}
