{
  "id": "20260626-github-991cb8c748",
  "title": "Significant-Gravitas/AutoGPT",
  "source": "github_trending",
  "source_url": "https://github.com/Significant-Gravitas/AutoGPT",
  "summary": "AutoGPT 致力于实现人人可用的 AI 愿景，提供易用且可扩展的工具，让用户专注于核心任务。",
  "content": "AutoGPT 是一个开源项目，旨在让 AI 技术更加普及和易用。它提供了一套工具，使用户能够轻松构建和部署 AI 应用，而无需深入了解底层技术。该项目在 GitHub 上拥有超过 18.5 万颗星标，社区活跃度高，持续推动 AI 民主化。",
  "tags": [
    "AI",
    "AutoGPT",
    "开源",
    "Python",
    "GitHub 热点"
  ],
  "status": "draft",
  "published_at": null,
  "collected_at": "2026-06-26T19:00:44+08:00",
  "language": "Python",
  "score": 9.5,
  "metadata": {
    "author": "Significant-Gravitas",
    "stars": 185157,
    "forks": 46127,
    "daily_stars": 27,
    "weekly_stars": null,
    "monthly_stars": null,
    "stars_baseline_date": null,
    "feed_name": null,
    "category": "GitHub 热点 · Python"
  }
}
