{
  "id": "20260622-github-ab8c0d0275",
  "title": "music-assistant/server",
  "source": "github_trending",
  "source_url": "https://github.com/music-assistant/server",
  "summary": "Music Assistant 是一个免费开源的媒体库管理器，能够连接多种流媒体服务和广泛支持的智能音箱。其核心服务器需运行在始终在线的设备上，如 Raspberry Pi、NAS 或 Intel NUC 等。",
  "content": "Music Assistant 是一个免费、开源的媒体库管理器，旨在整合用户的流媒体服务和各种智能音箱。该项目的核心是服务器组件，它作为整个系统的中枢，必须部署在始终在线的设备上，例如 Raspberry Pi、NAS 或 Intel NUC 等。该项目在 GitHub 上受到广泛关注，拥有 2748 颗星和 465 个分支，近期周增长 642 颗星，显示出较强的社区活跃度。",
  "tags": [
    "开源",
    "媒体库管理",
    "流媒体",
    "智能音箱",
    "Python",
    "GitHub 热点"
  ],
  "status": "draft",
  "published_at": null,
  "collected_at": "2026-06-22T20:02:15+08:00",
  "language": "Python",
  "score": 8.5,
  "metadata": {
    "author": "music-assistant",
    "stars": 2748,
    "forks": 465,
    "daily_stars": null,
    "weekly_stars": 642,
    "monthly_stars": null,
    "stars_baseline_date": null,
    "feed_name": null,
    "category": "GitHub 热点 · Python"
  }
}
