{
  "id": "20260630-github-faed1e11d9",
  "title": "rerun-io/rerun",
  "source": "github_trending",
  "source_url": "https://github.com/rerun-io/rerun",
  "summary": "rerun-io/rerun 是一个用于多模态机器人数据的可视化、查询和流式处理工具，支持训练过程中的数据监控与分析。",
  "content": "该仓库提供了一套高效的数据可视化框架，专为多模态机器人数据设计，支持实时流式传输、查询和训练数据可视化。基于 Rust 语言开发，具有高性能和低延迟特性，适用于机器人、自动驾驶等领域的复杂数据分析和调试。",
  "tags": [
    "机器人",
    "多模态数据",
    "可视化",
    "Rust",
    "数据流",
    "训练监控"
  ],
  "status": "draft",
  "published_at": null,
  "collected_at": "2026-06-30T19:02:00+08:00",
  "language": "Rust",
  "score": 8.5,
  "metadata": {
    "author": "rerun-io",
    "stars": 11025,
    "forks": 779,
    "daily_stars": 16,
    "weekly_stars": null,
    "monthly_stars": null,
    "stars_baseline_date": null,
    "feed_name": null,
    "category": "GitHub 热点 · Rust"
  }
}
