{
  "id": "20260523-github-bf42021204",
  "title": "amruthpillai/reactive-resume",
  "source": "github_trending",
  "source_url": "https://github.com/amruthpillai/reactive-resume",
  "summary": "Reactive Resume 是一款注重隐私的简历生成器，完全安全、可定制、可移植、开源且永久免费。",
  "content": "Reactive Resume 是一款独特的简历生成工具，其核心设计理念是保护用户隐私。该工具完全开源，用户可以自由定制简历样式，并支持数据导出和跨平台使用。它承诺永久免费，无需担心付费墙或数据泄露风险。项目在 GitHub 上拥有 37,874 颗星和 4,277 个分支，近期周增星数达 1,052，显示出活跃的社区关注度。",
  "tags": [
    "简历生成器",
    "开源",
    "隐私保护",
    "TypeScript",
    "GitHub 热点"
  ],
  "status": "draft",
  "published_at": null,
  "collected_at": "2026-05-23T18:31:30+08:00",
  "language": "中文",
  "score": 8.5,
  "metadata": {
    "author": "amruthpillai",
    "stars": 37874,
    "forks": 4277,
    "daily_stars": null,
    "weekly_stars": 1052,
    "monthly_stars": null,
    "stars_baseline_date": null,
    "feed_name": null,
    "category": "GitHub 热点 · TypeScript"
  }
}
