{
  "id": "20260608-github-55adc2b2d1",
  "title": "AlistGo/alist",
  "source": "github_trending",
  "source_url": "https://github.com/AlistGo/alist",
  "summary": "AlistGo/alist 是一个支持多存储的文件列表/WebDAV 程序，基于 Gin 和 Solidjs 构建。",
  "content": "该项目是一个开源的文件管理和共享工具，支持多种存储后端（如本地文件系统、云存储等），并提供 WebDAV 协议访问。它使用 Go 语言开发，后端采用 Gin 框架，前端使用 Solidjs，具备高性能和易扩展性。截至收集日期，该项目在 GitHub 上拥有 49618 颗星和 7949 个 fork，每日新增星数约 11 颗，属于 GitHub 热点项目。",
  "tags": [
    "文件列表",
    "WebDAV",
    "多存储",
    "Gin",
    "Solidjs",
    "Go"
  ],
  "status": "draft",
  "published_at": null,
  "collected_at": "2026-06-08T19:36:46+08:00",
  "language": "Go",
  "score": 9.0,
  "metadata": {
    "author": "AlistGo",
    "stars": 49618,
    "forks": 7949,
    "daily_stars": 11,
    "weekly_stars": null,
    "monthly_stars": null,
    "stars_baseline_date": null,
    "feed_name": null,
    "category": "GitHub 热点 · Go"
  }
}
