{
  "id": "20260706-github-a860df894f",
  "title": "yorukot/superfile",
  "source": "github_trending",
  "source_url": "https://github.com/yorukot/superfile",
  "summary": "yorukot/superfile 是一个用 Go 语言开发的现代化终端文件管理器，以其美观和时尚的设计著称，在 GitHub 上获得了超过 1.8 万星标，近期热度持续上升。",
  "content": "该项目由 yorukot 开发，是一款主打美观与现代化体验的终端文件管理器。它利用 Go 语言的高性能和跨平台特性，为用户提供了一种在命令行环境下操作文件的优雅方式。superfile 的界面设计注重视觉美感，同时保持了终端工具的高效性。项目在 GitHub 上表现活跃，拥有 18436 个星标和 496 个复刻，周增长星标达到 806 个，显示出社区的高度关注和积极反馈。",
  "tags": [
    "Go",
    "终端文件管理器",
    "美观",
    "现代化",
    "GitHub 热点"
  ],
  "status": "draft",
  "published_at": null,
  "collected_at": "2026-07-06T21:40:17+08:00",
  "language": "Go",
  "score": 8.5,
  "metadata": {
    "author": "yorukot",
    "stars": 18436,
    "forks": 496,
    "daily_stars": null,
    "weekly_stars": 806,
    "monthly_stars": null,
    "stars_baseline_date": null,
    "feed_name": null,
    "category": "GitHub 热点 · Go"
  }
}
