{
  "id": "20260529-github-9fa69d5f53",
  "title": "presenton/presenton",
  "source": "github_trending",
  "source_url": "https://github.com/presenton/presenton",
  "summary": "presenton 是一个开源的 AI 演示文稿生成器，提供 API 接口，可作为 Gamma、Beautiful AI 和 Decktopus 的替代方案。",
  "content": "该项目名为 presenton，是一个基于 TypeScript 开发的开源 AI 演示文稿生成工具。它提供了 API 接口，允许用户通过编程方式生成演示文稿，旨在作为 Gamma、Beautiful AI 和 Decktopus 等商业工具的免费替代品。项目在 GitHub 上获得了 7389 颗星和 1188 个分支，周增长星数达 1740，显示出较高的社区关注度。",
  "tags": [
    "AI",
    "演示文稿生成",
    "开源",
    "API",
    "TypeScript",
    "Gamma替代",
    "Beautiful AI替代",
    "Decktopus替代"
  ],
  "status": "draft",
  "published_at": null,
  "collected_at": "2026-05-29T19:05:54+08:00",
  "language": "TypeScript",
  "score": 8.5,
  "metadata": {
    "author": "presenton",
    "stars": 7389,
    "forks": 1188,
    "daily_stars": null,
    "weekly_stars": 1740,
    "monthly_stars": null,
    "stars_baseline_date": null,
    "feed_name": null,
    "category": "GitHub 热点 · TypeScript"
  }
}
