{
  "id": "20260721-github-e321586282",
  "title": "likec4/likec4",
  "source": "github_trending",
  "source_url": "https://github.com/likec4/likec4",
  "summary": "LikeC4 是一个基于代码的软件架构可视化、协作与演进工具，能够从代码中生成实时且准确的架构图。",
  "content": "LikeC4 是一个开源的软件架构可视化工具，它允许开发者通过代码定义架构图，并自动生成实时、准确的图表。该项目旨在解决传统架构图容易过时的问题，通过将架构描述与代码绑定，确保图表始终与最新代码同步。它支持协作功能，团队成员可以共同编辑和演进架构。该工具使用 TypeScript 开发，在 GitHub 上获得了 3981 颗星和 279 个 fork，近期日增星数达 65，显示出较高的社区关注度。",
  "tags": [
    "软件架构",
    "可视化",
    "协作",
    "代码驱动",
    "TypeScript",
    "开源工具"
  ],
  "status": "draft",
  "published_at": null,
  "collected_at": "2026-07-21T19:43:24+08:00",
  "language": "TypeScript",
  "score": 8.5,
  "metadata": {
    "author": "likec4",
    "stars": 3981,
    "forks": 279,
    "daily_stars": 65,
    "weekly_stars": null,
    "monthly_stars": null,
    "stars_baseline_date": null,
    "feed_name": null,
    "category": "GitHub 热点 · TypeScript"
  }
}
