{
  "id": "20260627-github-e30f8dee0b",
  "title": "NVIDIA/SkillSpector",
  "source": "github_trending",
  "source_url": "https://github.com/NVIDIA/SkillSpector",
  "summary": "NVIDIA/SkillSpector 是一个针对 AI 代理技能的安全扫描器，用于检测漏洞、恶意模式和安全风险。",
  "content": "NVIDIA/SkillSpector 是一个专注于 AI 代理技能安全性的开源工具。它能够自动扫描 AI 代理的技能模块，识别潜在的漏洞、恶意代码模式以及安全风险，帮助开发者在部署前发现并修复安全问题。该项目由 NVIDIA 维护，在 GitHub 上获得了超过 11000 颗星，显示出社区的高度关注。",
  "tags": [
    "AI安全",
    "安全扫描",
    "漏洞检测",
    "恶意模式识别",
    "NVIDIA",
    "Python"
  ],
  "status": "draft",
  "published_at": null,
  "collected_at": "2026-06-27T18:39:46+08:00",
  "language": "Python",
  "score": 8.5,
  "metadata": {
    "author": "NVIDIA",
    "stars": 11031,
    "forks": 890,
    "daily_stars": null,
    "weekly_stars": 2752,
    "monthly_stars": null,
    "stars_baseline_date": null,
    "feed_name": null,
    "category": "GitHub 热点 · Python"
  }
}
