{
  "id": "20260718-github-5a29fb0d0b",
  "title": "Comparing Transformers and Hybrid Models at the Token Level",
  "source": "rss",
  "source_url": "https://arxiv.org/pdf/2606.20936",
  "summary": "该论文在 token 级别上比较了纯 Transformer 模型与混合模型（如 Transformer + RNN 或 CNN）的性能，探讨了不同架构在处理序列数据时的效率与准确性差异。",
  "content": "本文基于 arXiv 预印本（编号 2606.20936），系统性地对比了 Transformer 及其混合变体在 token 级别任务上的表现。研究涵盖了模型的计算复杂度、上下文捕获能力以及训练稳定性等关键指标，并提供了详细的实验数据支持。混合模型通过引入局部归纳偏置（如 RNN 或 CNN 模块）来弥补纯 Transformer 在长序列处理中的不足，而 Transformer 则凭借全局注意力机制在并行计算上保持优势。论文结论指出，混合架构在特定任务（如代码生成或细粒度文本分类）中可达到更优的平衡，但纯 Transformer 在大规模预训练场景下仍具竞争力。",
  "tags": [
    "Transformer",
    "混合模型",
    "Token级别",
    "序列建模",
    "深度学习",
    "自然语言处理"
  ],
  "status": "draft",
  "published_at": "2026-06-27T10:16:10-05:00",
  "collected_at": "2026-07-18T18:57:22+08:00",
  "language": "zh",
  "score": 8.5,
  "metadata": {
    "feed_name": "Lobsters AI",
    "category": "综合技术",
    "stars": null,
    "daily_stars": null,
    "weekly_stars": null,
    "monthly_stars": null,
    "stars_baseline_date": null
  }
}
