{
  "id": "20260525-github-afb2934b80",
  "title": "apernet/hysteria",
  "source": "github_trending",
  "source_url": "https://github.com/apernet/hysteria",
  "summary": "Hysteria 是一个功能强大、速度极快且抗审查的代理工具。",
  "content": "Hysteria 是一个基于 Go 语言开发的网络代理工具，以其卓越的性能和强大的抗审查能力著称。它通过自定义协议优化了网络传输效率，能够有效应对网络封锁和干扰，提供稳定、高速的代理服务。该项目在 GitHub 上拥有超过 2.1 万颗星标，社区活跃，持续更新。",
  "tags": [
    "代理",
    "抗审查",
    "网络工具",
    "Go",
    "GitHub 热点"
  ],
  "status": "draft",
  "published_at": null,
  "collected_at": "2026-05-25T19:23:15+08:00",
  "language": "Go",
  "score": 8.5,
  "metadata": {
    "author": "apernet",
    "stars": 21534,
    "forks": 2199,
    "daily_stars": null,
    "weekly_stars": 501,
    "monthly_stars": null,
    "stars_baseline_date": null,
    "feed_name": null,
    "category": "GitHub 热点 · Go"
  }
}
