{
  "id": "20260520-github-89d9404787",
  "title": "ArthurBrussee/brush",
  "source": "github_trending",
  "source_url": "https://github.com/ArthurBrussee/brush",
  "summary": "ArthurBrussee/brush 是一个基于 Rust 的 3D 重建项目，旨在为所有人提供便捷的 3D 重建解决方案。",
  "content": "该项目由 ArthurBrussee 开发，在 GitHub 上获得 4567 颗星和 251 个分支，周增长 386 星，属于 Rust 语言的热门仓库。它专注于简化 3D 重建流程，可能涉及点云处理、网格生成或神经渲染等技术，适合开发者、研究人员和爱好者使用。",
  "tags": [
    "3D 重建",
    "Rust",
    "计算机视觉",
    "开源工具",
    "GitHub 热点"
  ],
  "status": "draft",
  "published_at": null,
  "collected_at": "2026-05-20T19:02:31+08:00",
  "language": "Rust",
  "score": 8.5,
  "metadata": {
    "author": "ArthurBrussee",
    "stars": 4567,
    "forks": 251,
    "daily_stars": null,
    "weekly_stars": 386,
    "monthly_stars": null,
    "stars_baseline_date": null,
    "feed_name": null,
    "category": "GitHub 热点 · Rust"
  }
}
