{
  "id": "20260602-github-db11269944",
  "title": "D4Vinci/Scrapling",
  "source": "github_trending",
  "source_url": "https://github.com/D4Vinci/Scrapling",
  "summary": "Scrapling 是一个自适应的 Web 抓取框架，能够处理从单个请求到大规模爬取的所有任务。",
  "content": "Scrapling 是一个用 Python 编写的自适应 Web 抓取框架，由 D4Vinci 开发。它旨在简化从简单请求到全面爬取的各种场景，提供灵活的配置和高效的性能。该框架在 GitHub 上获得了 58661 颗星和 5678 个分支，每日新增星数达 1486，显示出极高的社区关注度。其核心优势在于自适应能力，能够根据目标网站的结构变化自动调整抓取策略，降低维护成本。适用于数据采集、内容聚合、监控等场景。",
  "tags": [
    "Web 抓取",
    "爬虫框架",
    "Python",
    "自适应",
    "数据采集"
  ],
  "status": "draft",
  "published_at": null,
  "collected_at": "2026-06-02T19:29:48+08:00",
  "language": "Python",
  "score": 9.0,
  "metadata": {
    "author": "D4Vinci",
    "stars": 58661,
    "forks": 5678,
    "daily_stars": 1486,
    "weekly_stars": null,
    "monthly_stars": null,
    "stars_baseline_date": null,
    "feed_name": null,
    "category": "GitHub 热点 · Python"
  }
}
