{
  "id": "20260703-github-0a8155df68",
  "title": "AI can't be listed as inventor on patent applications, Japan's top court rules",
  "source": "rss",
  "source_url": "https://japannews.yomiuri.co.jp/science-nature/technology/20260306-314930/",
  "summary": "日本最高法院裁定人工智能不能列为专利申请的发明人。",
  "content": "根据日本最高法院的最新裁决，人工智能（AI）不能被列为专利申请的发明人。这一判决明确了在专利法律框架下，只有人类才能被认定为发明人，AI系统不具备法律人格，因此不能作为发明人出现在专利申请中。该裁决对AI在创新领域的法律地位产生了重要影响，可能引发关于AI生成发明的知识产权归属的进一步讨论。",
  "tags": [
    "AI",
    "专利",
    "日本",
    "法律",
    "知识产权"
  ],
  "status": "draft",
  "published_at": "2026-07-02T13:43:41+00:00",
  "collected_at": "2026-07-03T20:05:07+08:00",
  "language": "zh",
  "score": 8.5,
  "metadata": {
    "feed_name": "Hacker News Best (AI related)",
    "category": "综合技术",
    "stars": null,
    "daily_stars": null,
    "weekly_stars": null,
    "monthly_stars": null,
    "stars_baseline_date": null
  }
}
