{
  "id": "20260618-github-1360ce313c",
  "title": "cypress-io/cypress",
  "source": "github_trending",
  "source_url": "https://github.com/cypress-io/cypress",
  "summary": "Cypress 是一个快速、简单且可靠的浏览器端测试工具，适用于任何在浏览器中运行的内容。",
  "content": "Cypress 是一个基于 TypeScript 开发的前端测试框架，旨在为开发者提供快速、简单且可靠的测试体验。它支持端到端测试、组件测试和集成测试，能够直接在浏览器中运行，并提供实时重载、时间旅行调试等强大功能。该仓库由 cypress-io 维护，在 GitHub 上拥有超过 5 万颗星标和 3400 多个分支，近期周增星标 648 颗，属于 TypeScript 语言的热门项目。",
  "tags": [
    "测试框架",
    "前端测试",
    "端到端测试",
    "TypeScript",
    "浏览器测试",
    "Cypress"
  ],
  "status": "draft",
  "published_at": null,
  "collected_at": "2026-06-18T19:23:03+08:00",
  "language": "TypeScript",
  "score": 9.2,
  "metadata": {
    "author": "cypress-io",
    "stars": 50324,
    "forks": 3427,
    "daily_stars": null,
    "weekly_stars": 648,
    "monthly_stars": null,
    "stars_baseline_date": null,
    "feed_name": null,
    "category": "GitHub 热点 · TypeScript"
  }
}
